flake8_printf_formatting.py
flake8_printf_formatting-1.1.2.dist-info/LICENSE
flake8_printf_formatting-1.1.2.dist-info/METADATA
flake8_printf_formatting-1.1.2.dist-info/WHEEL
flake8_printf_formatting-1.1.2.dist-info/entry_points.txt
flake8_printf_formatting-1.1.2.dist-info/top_level.txt
flake8_printf_formatting-1.1.2.dist-info/RECORD
