Metadata-Version: 2.1
Name: flake8-printf-formatting
Version: 1.1.2
Summary: flake8 plugin which forbids printf-style string formatting
Home-page: https://github.com/atugushev/flake8-printf-formatting
Author: Albert Tugushev
Author-email: albert@tugushev.ru
License: MIT
Platform: UNKNOWN
Classifier: Framework :: Flake8
Classifier: License :: OSI Approved :: MIT License
Classifier: Programming Language :: Python :: 3
Classifier: Programming Language :: Python :: 3 :: Only
Classifier: Programming Language :: Python :: 3.6
Classifier: Programming Language :: Python :: 3.7
Classifier: Programming Language :: Python :: 3.8
Classifier: Programming Language :: Python :: 3.9
Classifier: Topic :: Software Development :: Quality Assurance
Requires-Python: >=3.6
